<?xml version="1.0" encoding="UTF-8"?><definitions xmlns="http://www.omg.org/spec/BPMN/20100524/MODEL" xmlns:bpmndi="http://www.omg.org/spec/BPMN/20100524/DI" xmlns:omgdc="http://www.omg.org/spec/DD/20100524/DC" xmlns:omgdi="http://www.omg.org/spec/DD/20100524/DI" xmlns:signavio="http://www.signavio.com" xmlns:xsi="http://www.w3.org/2001/XMLSchema-instance" exporter="Signavio Process Editor, http://www.signavio.com" exporterVersion="17.6.1" expressionLanguage="http://www.w3.org/TR/XPath" id="sid-4b57c721-a72f-4649-a57d-b2c81f385228" targetNamespace="http://www.signavio.com" typeLanguage="http://www.w3.org/2001/XMLSchema" xsi:schemaLocation="http://www.omg.org/spec/BPMN/20100524/MODEL http://www.omg.org/spec/BPMN/2.0/20100501/BPMN20.xsd">
   <process id="sid-76bcbdd2-77ac-46fe-9697-d3b32af00f83" isClosed="false" isExecutable="false" processType="None">
      <extensionElements>
         <signavio:signavioDiagramMetaData metaKey="clqrqid" metaValue=""/>
         <signavio:signavioDiagramMetaData metaKey="meta-emailadresseautor" metaValue="@vr-finanzdienstleistung.de"/>
         <signavio:signavioDiagramMetaData metaKey="meta-solutionprocessflows" metaValue=""/>
         <signavio:signavioDiagramMetaData metaKey="meta-countryregionrelevance" metaValue=""/>
         <signavio:signavioDiagramMetaData metaKey="pmcontact" metaValue=""/>
         <signavio:signavioDiagramMetaData metaKey="processtype" metaValue=""/>
         <signavio:signavioDiagramMetaData metaKey="meta-date" metaValue=""/>
         <signavio:signavioDiagramMetaData metaKey="meta-lieferantdesinputs" metaValue=""/>
         <signavio:signavioDiagramMetaData metaKey="meta-m2processperformancecockpit" metaValue=""/>
         <signavio:signavioDiagramMetaData metaKey="clcontrolid" metaValue=""/>
         <signavio:signavioDiagramMetaData metaKey="objective" metaValue=""/>
         <signavio:signavioDiagramMetaData metaKey="itsystems" metaValue=""/>
         <signavio:signavioDiagramMetaData metaKey="meta-product" metaValue=""/>
         <signavio:signavioDiagramMetaData metaKey="meta-valuedriver" metaValue=""/>
         <signavio:signavioDiagramMetaData metaKey="mitgeltendedokumente" metaValue=""/>
         <signavio:signavioDiagramMetaData metaKey="meta-modelingstatus" metaValue="Draft"/>
         <signavio:signavioDiagramMetaData metaKey="iso9000ff" metaValue=""/>
         <signavio:signavioDiagramMetaData metaKey="meta-m3annualimprovementtargets2" metaValue=""/>
         <signavio:signavioDiagramMetaData metaKey="meta-mcdorganization" metaValue=""/>
         <signavio:signavioDiagramMetaData metaKey="processslas" metaValue=""/>
         <signavio:signavioDiagramMetaData metaKey="meta-processgoal" metaValue=""/>
         <signavio:signavioDiagramMetaData metaKey="meta-mcdlinkofpublishedprocess" metaValue=""/>
         <signavio:signavioDiagramMetaData metaKey="meta-modularprocess" metaValue=""/>
         <signavio:signavioDiagramMetaData metaKey="meta-clouddeliveryprocesschanged" metaValue=""/>
         <signavio:signavioDiagramMetaData metaKey="ikskontrolle" metaValue=""/>
         <signavio:signavioDiagramMetaData metaKey="meta-efihierarchykey" metaValue=""/>
         <signavio:signavioDiagramMetaData metaKey="businessownernew" metaValue=""/>
         <signavio:signavioDiagramMetaData metaKey="prozessanalystin" metaValue=""/>
         <signavio:signavioDiagramMetaData metaKey="processlinks" metaValue=""/>
         <signavio:signavioDiagramMetaData metaKey="meta-arissaptype" metaValue=""/>
         <signavio:signavioDiagramMetaData metaKey="meta-cycsemanticvalidation" metaValue=""/>
         <signavio:signavioDiagramMetaData metaKey="generalprocessstatus" metaValue="InProcess"/>
         <signavio:signavioDiagramMetaData metaKey="meta-generalrelateddiagrams" metaValue=""/>
         <signavio:signavioDiagramMetaData metaKey="prozesskategorie" metaValue=""/>
         <signavio:signavioDiagramMetaData metaKey="sfregion" metaValue=""/>
         <signavio:signavioDiagramMetaData metaKey="certificationstandards" metaValue=""/>
         <signavio:signavioDiagramMetaData metaKey="generalplannedprocessmaturitylev" metaValue=""/>
         <signavio:signavioDiagramMetaData metaKey="meta-generalexternalprocessdocum" metaValue=""/>
         <signavio:signavioDiagramMetaData metaKey="prozessanalyst" metaValue=""/>
         <signavio:signavioDiagramMetaData metaKey="effectifprozessverantwortlicherb" metaValue=""/>
         <signavio:signavioDiagramMetaData metaKey="meta-clouddeliveryprocesschanger" metaValue=""/>
         <signavio:signavioDiagramMetaData metaKey="meta-clouddeliveryprocesschangev" metaValue=""/>
         <signavio:signavioDiagramMetaData metaKey="meta-usedin" metaValue=""/>
         <signavio:signavioDiagramMetaData metaKey="meta-deliverymodel" metaValue=""/>
         <signavio:signavioDiagramMetaData metaKey="anforderungen" metaValue=""/>
         <signavio:signavioDiagramMetaData metaKey="meta-mcdservicearea" metaValue=""/>
         <signavio:signavioDiagramMetaData metaKey="processstatus" metaValue=""/>
         <signavio:signavioDiagramMetaData metaKey="topgoall3process2014" metaValue=""/>
         <signavio:signavioDiagramMetaData metaKey="meta-idwpsrelevant" metaValue=""/>
         <signavio:signavioDiagramMetaData metaKey="meta-inframework" metaValue=""/>
         <signavio:signavioDiagramMetaData metaKey="meta-sapstandardcontent" metaValue=""/>
         <signavio:signavioDiagramMetaData metaKey="meta-geltungsbereich" metaValue=""/>
         <signavio:signavioDiagramMetaData metaKey="meta-mcdoperationalprocessid" metaValue=""/>
         <signavio:signavioDiagramMetaData metaKey="meta-m2detailedprocessdocumentat" metaValue=""/>
         <signavio:signavioDiagramMetaData metaKey="meta-prozessverantwortlicher2" metaValue=""/>
         <signavio:signavioDiagramMetaData metaKey="meta-sfregion" metaValue=""/>
         <signavio:signavioDiagramMetaData metaKey="meta-eingangswege" metaValue=""/>
         <signavio:signavioDiagramMetaData metaKey="palevel" metaValue=""/>
         <signavio:signavioDiagramMetaData metaKey="prozessinput" metaValue=""/>
         <signavio:signavioDiagramMetaData metaKey="meta-emailadresse" metaValue="@vr-finanzdienstleistung.de"/>
         <signavio:signavioDiagramMetaData metaKey="meta-generalrelateddiagrams2" metaValue=""/>
         <signavio:signavioDiagramMetaData metaKey="meta-m3annualimprovementtargetsn" metaValue=""/>
         <signavio:signavioDiagramMetaData metaKey="prozessscope" metaValue=""/>
         <signavio:signavioDiagramMetaData metaKey="meta-mcdprocesschecklist" metaValue=""/>
         <signavio:signavioDiagramMetaData metaKey="meta-m2processcontinuityplan" metaValue=""/>
         <signavio:signavioDiagramMetaData metaKey="meta-processslas" metaValue=""/>
         <signavio:signavioDiagramMetaData metaKey="effectifprozessverantwortlicher" metaValue=""/>
         <signavio:signavioDiagramMetaData metaKey="prozessverantwortlicher" metaValue=""/>
         <signavio:signavioDiagramMetaData metaKey="meta-processparticipant2" metaValue=""/>
         <signavio:signavioDiagramMetaData metaKey="meta-processparticipant1" metaValue=""/>
         <signavio:signavioDiagramMetaData metaKey="meta-businessunit" metaValue=""/>
         <signavio:signavioDiagramMetaData metaKey="meta-generalquarterendclosingqec" metaValue=""/>
         <signavio:signavioDiagramMetaData metaKey="meta-m2processcontinuitystatus" metaValue=""/>
         <signavio:signavioDiagramMetaData metaKey="meta-verb" metaValue=""/>
         <signavio:signavioDiagramMetaData metaKey="normen" metaValue=""/>
         <signavio:signavioDiagramMetaData metaKey="meta-efiideasupport" metaValue=""/>
         <signavio:signavioDiagramMetaData metaKey="meta-lastreviewedon" metaValue=""/>
         <signavio:signavioDiagramMetaData metaKey="meta-m3onlinerealtimeprocessdat2" metaValue=""/>
         <signavio:signavioDiagramMetaData metaKey="meta-m1knowledgetransfertext" metaValue=""/>
         <signavio:signavioDiagramMetaData metaKey="meta-maturityassessment" metaValue=""/>
         <signavio:signavioDiagramMetaData metaKey="clriskid" metaValue=""/>
         <signavio:signavioDiagramMetaData metaKey="meta-anweisungenimvorgang" metaValue=""/>
         <signavio:signavioDiagramMetaData metaKey="m2processvariants" metaValue=""/>
         <signavio:signavioDiagramMetaData metaKey="meta-setupguide" metaValue=""/>
         <signavio:signavioDiagramMetaData metaKey="meta-zertifizierung" metaValue=""/>
         <signavio:signavioDiagramMetaData metaKey="topgoalppi2014" metaValue=""/>
         <signavio:signavioDiagramMetaData metaKey="meta-bpxtodel" metaValue=""/>
         <signavio:signavioDiagramMetaData metaKey="meta-testscript2" metaValue=""/>
         <signavio:signavioDiagramMetaData metaKey="executable" metaValue=""/>
         <signavio:signavioDiagramMetaData metaKey="slbespokefla" metaValue=""/>
         <signavio:signavioDiagramMetaData metaKey="meta-lastreviewcommentm" metaValue=""/>
         <signavio:signavioDiagramMetaData metaKey="meta-maturitylevel1" metaValue=""/>
         <signavio:signavioDiagramMetaData metaKey="meta-setupusingcloudintegrationa" metaValue=""/>
         <signavio:signavioDiagramMetaData metaKey="meta-riskcontrol" metaValue=""/>
         <signavio:signavioDiagramMetaData metaKey="meta-scopeitemversion" metaValue=""/>
         <signavio:signavioDiagramMetaData metaKey="meta-mcdprocessslasandkpis" metaValue=""/>
         <signavio:signavioDiagramMetaData metaKey="fitfunction" metaValue=""/>
         <signavio:signavioDiagramMetaData metaKey="meta-vorgangsvorlage" metaValue=""/>
         <signavio:signavioDiagramMetaData metaKey="meta-executioncoststotal" metaValue=""/>
         <signavio:signavioDiagramMetaData metaKey="meta-processowner" metaValue=""/>
         <signavio:signavioDiagramMetaData metaKey="meta-prozesseigner" metaValue=""/>
         <signavio:signavioDiagramMetaData metaKey="meta-m3output" metaValue=""/>
         <signavio:signavioDiagramMetaData metaKey="meta-maturityassessmentdetailedv" metaValue=""/>
         <signavio:signavioDiagramMetaData metaKey="meta-itapplications" metaValue=""/>
         <signavio:signavioDiagramMetaData metaKey="meta-kundedesoutputs2" metaValue=""/>
         <signavio:signavioDiagramMetaData metaKey="meta-clriskid" metaValue="N/A"/>
         <signavio:signavioDiagramMetaData metaKey="meta-generalprocessnumber" metaValue=""/>
         <signavio:signavioDiagramMetaData metaKey="sflevel" metaValue=""/>
         <signavio:signavioDiagramMetaData metaKey="meta-businessdeliverables" metaValue=""/>
         <signavio:signavioDiagramMetaData metaKey="meta-m3processstandardizationne2" metaValue=""/>
         <signavio:signavioDiagramMetaData metaKey="meta-clqrqid" metaValue="N/A"/>
         <signavio:signavioDiagramMetaData metaKey="meta-kunde" metaValue=""/>
         <signavio:signavioDiagramMetaData metaKey="meta-m1knowledgetransfertext3" metaValue=""/>
         <signavio:signavioDiagramMetaData metaKey="meta-m1knowledgetransfertext2" metaValue=""/>
         <signavio:signavioDiagramMetaData metaKey="meta-ml" metaValue=""/>
         <signavio:signavioDiagramMetaData metaKey="generalactualprocessmaturityleve" metaValue=""/>
         <signavio:signavioDiagramMetaData metaKey="meta-m3singletaskingnew" metaValue=""/>
         <signavio:signavioDiagramMetaData metaKey="sfsme" metaValue=""/>
         <signavio:signavioDiagramMetaData metaKey="meta-keyprocessflows" metaValue=""/>
         <signavio:signavioDiagramMetaData metaKey="slbespokeflag" metaValue="No"/>
         <signavio:signavioDiagramMetaData metaKey="meta-clouddeliveryprocesscha" metaValue=""/>
         <signavio:signavioDiagramMetaData metaKey="processmanagernew" metaValue=""/>
         <signavio:signavioDiagramMetaData metaKey="meta-processgoal2" metaValue=""/>
         <signavio:signavioDiagramMetaData metaKey="meta-standardindividual" metaValue=""/>
         <signavio:signavioDiagramMetaData metaKey="generalprocessoccurrence" metaValue=""/>
         <signavio:signavioDiagramMetaData metaKey="meta-endtoendscenario" metaValue=""/>
         <signavio:signavioDiagramMetaData metaKey="externaldocuments" metaValue=""/>
         <signavio:signavioDiagramMetaData metaKey="market" metaValue=""/>
         <signavio:signavioDiagramMetaData metaKey="meta-teilprozesseigner" metaValue=""/>
         <signavio:signavioDiagramMetaData metaKey="meta-overview" metaValue=""/>
         <signavio:signavioDiagramMetaData metaKey="meta-prozesskategorie" metaValue=""/>
         <signavio:signavioDiagramMetaData metaKey="meta-m3onlinerealtimeprocessdata" metaValue=""/>
         <signavio:signavioDiagramMetaData metaKey="prozessrelevantedokumente" metaValue=""/>
         <signavio:signavioDiagramMetaData metaKey="exchange" metaValue=""/>
         <signavio:signavioDiagramMetaData metaKey="meta-flligam" metaValue=""/>
         <signavio:signavioDiagramMetaData metaKey="meta-legalentity2" metaValue=""/>
         <signavio:signavioDiagramMetaData metaKey="meta-mcdprocessprimaryresponsibl" metaValue=""/>
         <signavio:signavioDiagramMetaData metaKey="meta-prozessreifegrad" metaValue=""/>
         <signavio:signavioDiagramMetaData metaKey="meta-accessmaturityassessmenther" metaValue="https://workflow.signavio.com/sapprocessmapworkspacesimonblattmann/cases/start/610b89d4017af21cafa24b87"/>
         <signavio:signavioDiagramMetaData metaKey="meta-businessunit2" metaValue=""/>
         <signavio:signavioDiagramMetaData metaKey="meta-tasktutorials" metaValue=""/>
         <signavio:signavioDiagramMetaData metaKey="meta-m2processperformancecockpi2" metaValue=""/>
         <signavio:signavioDiagramMetaData metaKey="meta-m3processstandardizationnew" metaValue=""/>
         <signavio:signavioDiagramMetaData metaKey="meta-efikeywordsandtags" metaValue=""/>
         <signavio:signavioDiagramMetaData metaKey="meta-prozesseinordnung" metaValue=""/>
         <signavio:signavioDiagramMetaData metaKey="meta-emailadressefg" metaValue="@vr-finanzdienstleistung.de"/>
         <signavio:signavioDiagramMetaData metaKey="meta-itsystem" metaValue=""/>
         <signavio:signavioDiagramMetaData metaKey="prozessoutput" metaValue=""/>
         <signavio:signavioDiagramMetaData metaKey="meta-vertraulichkeit" metaValue="Nur für den internen Gebrauch"/>
         <signavio:signavioDiagramMetaData metaKey="m1processonepagerneu" metaValue=""/>
         <signavio:signavioDiagramMetaData metaKey="m2processriskquestionaire" metaValue=""/>
         <signavio:signavioDiagramMetaData metaKey="meta-clcontrolid" metaValue="N/A"/>
         <signavio:signavioDiagramMetaData metaKey="bapol3responsiblenew" metaValue=""/>
         <signavio:signavioDiagramMetaData metaKey="meta-kennzahlen" metaValue=""/>
         <signavio:signavioDiagramMetaData metaKey="legalentity" metaValue=""/>
         <signavio:signavioDiagramMetaData metaKey="meta-businessbenefits" metaValue=""/>
         <signavio:signavioDiagramMetaData metaKey="meta-gltigkeitasdauer" metaValue=""/>
         <signavio:signavioDiagramMetaData metaKey="prozessreifegrad" metaValue=""/>
         <signavio:signavioDiagramMetaData metaKey="m2detailedprocessdocumentation" metaValue=""/>
         <signavio:signavioDiagramMetaData metaKey="sfopsbu" metaValue=""/>
         <signavio:signavioDiagramMetaData metaKey="meta-mynumber" metaValue=""/>
         <signavio:signavioDiagramMetaData metaKey="meta-artikelnr" metaValue=""/>
         <signavio:signavioDiagramMetaData metaKey="m3processvisionlongtermneu" metaValue=""/>
         <signavio:signavioDiagramMetaData metaKey="meta-m3continuousimprovementproc" metaValue=""/>
         <signavio:signavioDiagramMetaData metaKey="sfreviewer" metaValue=""/>
         <signavio:signavioDiagramMetaData metaKey="meta-arissapid" metaValue=""/>
         <signavio:signavioDiagramMetaData metaKey="prozessstufe" metaValue=""/>
         <signavio:signavioDiagramMetaData metaKey="meta-sh" metaValue=""/>
         <signavio:signavioDiagramMetaData metaKey="meta-kpmanager" metaValue=""/>
         <signavio:signavioDiagramMetaData metaKey="generalexternalprocessdocumentat" metaValue=""/>
         <signavio:signavioDiagramMetaData metaKey="meta-bestpractices" metaValue=""/>
         <signavio:signavioDiagramMetaData metaKey="sfmodeller" metaValue=""/>
         <signavio:signavioDiagramMetaData metaKey="revisionid" metaValue="c0f7b26c7f154a7db5199a28def0930a"/>
      </extensionElements>
      <startEvent id="sid-5F5D86D5-D873-489A-8300-D35D4386FAD5">
         <extensionElements>
            <signavio:signavioMetaData metaKey="bgcolor" metaValue="#ffffff"/>
            <signavio:signavioMetaData metaKey="bordercolor" metaValue="#000000"/>
            <signavio:signavioMetaData metaKey="meta-preceedingprocesses" metaValue=""/>
            <signavio:signavioMetaData metaKey="vorgngerprozesse" metaValue=""/>
            <signavio:signavioMetaData metaKey="preceedingprocesses" metaValue=""/>
            <signavio:signavioMetaData metaKey="links" metaValue=""/>
            <signavio:signavioMetaData metaKey="meta-vorgngerprozesse" metaValue=""/>
         </extensionElements>
         <outgoing>sid-651B3646-CE12-4318-AD49-0E4A923044EC</outgoing>
      </startEvent>
      <endEvent id="sid-FC1426C9-AAE7-473D-BAE8-6F10C59B7A74">
         <extensionElements>
            <signavio:signavioMetaData metaKey="bgcolor" metaValue="#ffffff"/>
            <signavio:signavioMetaData metaKey="bordercolor" metaValue="#000000"/>
            <signavio:signavioMetaData metaKey="meta-nachfolgerprozesse" metaValue=""/>
            <signavio:signavioMetaData metaKey="folgeprozess" metaValue=""/>
            <signavio:signavioMetaData metaKey="followingprocesses" metaValue=""/>
            <signavio:signavioMetaData metaKey="meta-succeedingprocesses" metaValue=""/>
            <signavio:signavioMetaData metaKey="nachfolgerprozesse" metaValue=""/>
         </extensionElements>
         <incoming>sid-BF4F50B5-1556-4A3C-9D2A-A0A0C347DEB5</incoming>
      </endEvent>
      <task completionQuantity="1" id="sid-EDFCFD39-8583-45B8-91B3-8E1A9CE45900" isForCompensation="false" name="0" startQuantity="1">
         <extensionElements>
            <signavio:signavioMetaData metaKey="bgcolor" metaValue="#FFFFFF"/>
            <signavio:signavioMetaData metaKey="bordercolor" metaValue="#000000"/>
            <signavio:signavioMetaData metaKey="meta-solutionprocessflows" metaValue=""/>
            <signavio:signavioMetaData metaKey="meta-responsible" metaValue=""/>
            <signavio:signavioMetaData metaKey="erteiltfreigabe" metaValue=""/>
            <signavio:signavioMetaData metaKey="clbcpid" metaValue="N/A"/>
            <signavio:signavioMetaData metaKey="wirdkonsultiert" metaValue=""/>
            <signavio:signavioMetaData metaKey="meta-clriskid" metaValue="N/A"/>
            <signavio:signavioMetaData metaKey="meta-executioncosts" metaValue=""/>
            <signavio:signavioMetaData metaKey="meta-date" metaValue=""/>
            <signavio:signavioMetaData metaKey="meta-accountable" metaValue=""/>
            <signavio:signavioMetaData metaKey="iks" metaValue=""/>
            <signavio:signavioMetaData metaKey="fhrtzustzlichdurch" metaValue=""/>
            <signavio:signavioMetaData metaKey="itsystems" metaValue=""/>
            <signavio:signavioMetaData metaKey="meta-erteiltfreigabe2" metaValue=""/>
            <signavio:signavioMetaData metaKey="clrqid" metaValue="N/A"/>
            <signavio:signavioMetaData metaKey="meta-myglossarylink" metaValue=""/>
            <signavio:signavioMetaData metaKey="meta-screenflow" metaValue=""/>
            <signavio:signavioMetaData metaKey="meta-informed" metaValue=""/>
            <signavio:signavioMetaData metaKey="mitgeltendedokumente" metaValue=""/>
            <signavio:signavioMetaData metaKey="startid" metaValue=""/>
            <signavio:signavioMetaData metaKey="meta-ml" metaValue=""/>
            <signavio:signavioMetaData metaKey="additionallyresponsible" metaValue=""/>
            <signavio:signavioMetaData metaKey="booleanInfo2" metaValue=""/>
            <signavio:signavioMetaData metaKey="meta-processinsightsmetricsavail" metaValue=""/>
            <signavio:signavioMetaData metaKey="myDateIshInfo" metaValue=""/>
            <signavio:signavioMetaData metaKey="isresponsible" metaValue=""/>
            <signavio:signavioMetaData metaKey="accountable" metaValue=""/>
            <signavio:signavioMetaData metaKey="endanchor" metaValue=""/>
            <signavio:signavioMetaData metaKey="slbespokeflag" metaValue="No"/>
            <signavio:signavioMetaData metaKey="meta-istgesamtverwantwortlich" metaValue=""/>
            <signavio:signavioMetaData metaKey="externaldocuments2" metaValue=""/>
            <signavio:signavioMetaData metaKey="ikskontrolle" metaValue=""/>
            <signavio:signavioMetaData metaKey="sla" metaValue=""/>
            <signavio:signavioMetaData metaKey="meta-arissaptype" metaValue=""/>
            <signavio:signavioMetaData metaKey="meta-processinsightsmetricdetail" metaValue=""/>
            <signavio:signavioMetaData metaKey="externaldocuments" metaValue=""/>
            <signavio:signavioMetaData metaKey="meta-bestpracticedocument" metaValue=""/>
            <signavio:signavioMetaData metaKey="vorlagenliste" metaValue=""/>
            <signavio:signavioMetaData metaKey="meta-externaldocuments" metaValue=""/>
            <signavio:signavioMetaData metaKey="prozessrelevantedokumente" metaValue=""/>
            <signavio:signavioMetaData metaKey="meta-erteiltfreigabe" metaValue=""/>
            <signavio:signavioMetaData metaKey="meta-riskandcontrols" metaValue=""/>
            <signavio:signavioMetaData metaKey="meta-importance" metaValue=""/>
            <signavio:signavioMetaData metaKey="risksactivity" metaValue=""/>
            <signavio:signavioMetaData metaKey="systemid" metaValue=""/>
            <signavio:signavioMetaData metaKey="meta-itsystem" metaValue=""/>
            <signavio:signavioMetaData metaKey="meta-mcdtaskactivityprerequisite" metaValue=""/>
            <signavio:signavioMetaData metaKey="meta-erteiltfreigabe22" metaValue=""/>
            <signavio:signavioMetaData metaKey="doclink" metaValue=""/>
            <signavio:signavioMetaData metaKey="fhrtdurch" metaValue=""/>
            <signavio:signavioMetaData metaKey="myDateIshInfo2" metaValue=""/>
            <signavio:signavioMetaData metaKey="zahl" metaValue=""/>
            <signavio:signavioMetaData metaKey="meta-consulted" metaValue=""/>
            <signavio:signavioMetaData metaKey="innererevision" metaValue=""/>
            <signavio:signavioMetaData metaKey="cliscontrolflag" metaValue=""/>
            <signavio:signavioMetaData metaKey="responsible" metaValue=""/>
            <signavio:signavioMetaData metaKey="meta-externaldocuments2" metaValue=""/>
            <signavio:signavioMetaData metaKey="liegezeiten" metaValue=""/>
            <signavio:signavioMetaData metaKey="meta-signalmetricsavailabletomea" metaValue=""/>
            <signavio:signavioMetaData metaKey="meta-issues" metaValue=""/>
            <signavio:signavioMetaData metaKey="wirdinformiert" metaValue=""/>
            <signavio:signavioMetaData metaKey="informed" metaValue=""/>
            <signavio:signavioMetaData metaKey="risikenundkontrollen" metaValue=""/>
            <signavio:signavioMetaData metaKey="meta-risklevel" metaValue="None"/>
            <signavio:signavioMetaData metaKey="ikskontrollen" metaValue=""/>
            <signavio:signavioMetaData metaKey="istgesamtverantwortlich" metaValue=""/>
            <signavio:signavioMetaData metaKey="urlInfo2" metaValue=""/>
            <signavio:signavioMetaData metaKey="meta-ubmclicks" metaValue=""/>
            <signavio:signavioMetaData metaKey="urlInfo1" metaValue=""/>
            <signavio:signavioMetaData metaKey="additionalresponsible" metaValue=""/>
            <signavio:signavioMetaData metaKey="meta-arissapid" metaValue=""/>
            <signavio:signavioMetaData metaKey="consulted" metaValue=""/>
            <signavio:signavioMetaData metaKey="booleanInfo" metaValue=""/>
            <signavio:signavioMetaData metaKey="meta-sh" metaValue=""/>
            <signavio:signavioMetaData metaKey="meta-automatisiert" metaValue=""/>
            <signavio:signavioMetaData metaKey="meta-riskcontrol" metaValue=""/>
            <signavio:signavioMetaData metaKey="risks" metaValue=""/>
            <signavio:signavioMetaData metaKey="meta-dokumentenobjekte" metaValue=""/>
            <signavio:signavioMetaData metaKey="processlink" metaValue=""/>
            <signavio:signavioMetaData metaKey="meta-risikenundkontrollen" metaValue=""/>
            <signavio:signavioMetaData metaKey="meta-risks" metaValue=""/>
            <signavio:signavioMetaData metaKey="meta-capability" metaValue=""/>
            <signavio:signavioMetaData metaKey="meta-itsysteme" metaValue=""/>
            <signavio:signavioMetaData metaKey="bearbeitungszeiten" metaValue=""/>
            <signavio:signavioMetaData metaKey="risk" metaValue=""/>
            <signavio:signavioMetaData metaKey="meta-mtmexperiencejourney" metaValue=""/>
            <signavio:signavioMetaData metaKey="meta-momentthatmatters2" metaValue=""/>
         </extensionElements>
         <incoming>sid-651B3646-CE12-4318-AD49-0E4A923044EC</incoming>
         <outgoing>sid-7D9767FF-E6EB-4152-9C65-1B11D6262E68</outgoing>
      </task>
      <inclusiveGateway gatewayDirection="Diverging" id="sid-71173100-A04C-4DD0-AA9E-768DF423C145">
         <extensionElements>
            <signavio:signavioMetaData metaKey="bgcolor" metaValue="#ffffff"/>
            <signavio:signavioMetaData metaKey="bordercolor" metaValue="#000000"/>
            <signavio:signavioMetaData metaKey="adapterclassname" metaValue=""/>
            <signavio:signavioMetaData metaKey="adaptertype" metaValue=""/>
            <signavio:signavioMetaData metaKey="psiconfiguration" metaValue=""/>
         </extensionElements>
         <incoming>sid-7D9767FF-E6EB-4152-9C65-1B11D6262E68</incoming>
         <outgoing>sid-556F8EB4-4CB9-4370-9D83-4BCABC759443</outgoing>
         <outgoing>sid-5867DA7E-63B0-47C4-845D-ED539FE1A66C</outgoing>
         <outgoing>sid-DA60A646-4E09-46FC-B8B5-414DE5D41C8F</outgoing>
      </inclusiveGateway>
      <task completionQuantity="1" id="sid-AD61A674-0B58-41F2-B14D-53A0F6A0ED9A" isForCompensation="false" name="1" startQuantity="1">
         <extensionElements>
            <signavio:signavioMetaData metaKey="bgcolor" metaValue="#FFFFFF"/>
            <signavio:signavioMetaData metaKey="bordercolor" metaValue="#000000"/>
            <signavio:signavioMetaData metaKey="meta-solutionprocessflows" metaValue=""/>
            <signavio:signavioMetaData metaKey="meta-responsible" metaValue=""/>
            <signavio:signavioMetaData metaKey="erteiltfreigabe" metaValue=""/>
            <signavio:signavioMetaData metaKey="clbcpid" metaValue="N/A"/>
            <signavio:signavioMetaData metaKey="wirdkonsultiert" metaValue=""/>
            <signavio:signavioMetaData metaKey="meta-clriskid" metaValue="N/A"/>
            <signavio:signavioMetaData metaKey="meta-executioncosts" metaValue=""/>
            <signavio:signavioMetaData metaKey="meta-date" metaValue=""/>
            <signavio:signavioMetaData metaKey="meta-accountable" metaValue=""/>
            <signavio:signavioMetaData metaKey="iks" metaValue=""/>
            <signavio:signavioMetaData metaKey="fhrtzustzlichdurch" metaValue=""/>
            <signavio:signavioMetaData metaKey="itsystems" metaValue=""/>
            <signavio:signavioMetaData metaKey="meta-erteiltfreigabe2" metaValue=""/>
            <signavio:signavioMetaData metaKey="clrqid" metaValue="N/A"/>
            <signavio:signavioMetaData metaKey="meta-myglossarylink" metaValue=""/>
            <signavio:signavioMetaData metaKey="meta-screenflow" metaValue=""/>
            <signavio:signavioMetaData metaKey="meta-informed" metaValue=""/>
            <signavio:signavioMetaData metaKey="mitgeltendedokumente" metaValue=""/>
            <signavio:signavioMetaData metaKey="startid" metaValue=""/>
            <signavio:signavioMetaData metaKey="meta-ml" metaValue=""/>
            <signavio:signavioMetaData metaKey="additionallyresponsible" metaValue=""/>
            <signavio:signavioMetaData metaKey="booleanInfo2" metaValue=""/>
            <signavio:signavioMetaData metaKey="meta-processinsightsmetricsavail" metaValue=""/>
            <signavio:signavioMetaData metaKey="myDateIshInfo" metaValue=""/>
            <signavio:signavioMetaData metaKey="isresponsible" metaValue=""/>
            <signavio:signavioMetaData metaKey="accountable" metaValue=""/>
            <signavio:signavioMetaData metaKey="endanchor" metaValue=""/>
            <signavio:signavioMetaData metaKey="slbespokeflag" metaValue="No"/>
            <signavio:signavioMetaData metaKey="meta-istgesamtverwantwortlich" metaValue=""/>
            <signavio:signavioMetaData metaKey="externaldocuments2" metaValue=""/>
            <signavio:signavioMetaData metaKey="ikskontrolle" metaValue=""/>
            <signavio:signavioMetaData metaKey="sla" metaValue=""/>
            <signavio:signavioMetaData metaKey="meta-arissaptype" metaValue=""/>
            <signavio:signavioMetaData metaKey="meta-processinsightsmetricdetail" metaValue=""/>
            <signavio:signavioMetaData metaKey="externaldocuments" metaValue=""/>
            <signavio:signavioMetaData metaKey="meta-bestpracticedocument" metaValue=""/>
            <signavio:signavioMetaData metaKey="vorlagenliste" metaValue=""/>
            <signavio:signavioMetaData metaKey="meta-externaldocuments" metaValue=""/>
            <signavio:signavioMetaData metaKey="prozessrelevantedokumente" metaValue=""/>
            <signavio:signavioMetaData metaKey="meta-erteiltfreigabe" metaValue=""/>
            <signavio:signavioMetaData metaKey="meta-riskandcontrols" metaValue=""/>
            <signavio:signavioMetaData metaKey="meta-importance" metaValue=""/>
            <signavio:signavioMetaData metaKey="risksactivity" metaValue=""/>
            <signavio:signavioMetaData metaKey="systemid" metaValue=""/>
            <signavio:signavioMetaData metaKey="meta-itsystem" metaValue=""/>
            <signavio:signavioMetaData metaKey="meta-mcdtaskactivityprerequisite" metaValue=""/>
            <signavio:signavioMetaData metaKey="meta-erteiltfreigabe22" metaValue=""/>
            <signavio:signavioMetaData metaKey="doclink" metaValue=""/>
            <signavio:signavioMetaData metaKey="fhrtdurch" metaValue=""/>
            <signavio:signavioMetaData metaKey="myDateIshInfo2" metaValue=""/>
            <signavio:signavioMetaData metaKey="zahl" metaValue=""/>
            <signavio:signavioMetaData metaKey="meta-consulted" metaValue=""/>
            <signavio:signavioMetaData metaKey="innererevision" metaValue=""/>
            <signavio:signavioMetaData metaKey="cliscontrolflag" metaValue=""/>
            <signavio:signavioMetaData metaKey="responsible" metaValue=""/>
            <signavio:signavioMetaData metaKey="meta-externaldocuments2" metaValue=""/>
            <signavio:signavioMetaData metaKey="liegezeiten" metaValue=""/>
            <signavio:signavioMetaData metaKey="meta-signalmetricsavailabletomea" metaValue=""/>
            <signavio:signavioMetaData metaKey="meta-issues" metaValue=""/>
            <signavio:signavioMetaData metaKey="wirdinformiert" metaValue=""/>
            <signavio:signavioMetaData metaKey="informed" metaValue=""/>
            <signavio:signavioMetaData metaKey="risikenundkontrollen" metaValue=""/>
            <signavio:signavioMetaData metaKey="meta-risklevel" metaValue="None"/>
            <signavio:signavioMetaData metaKey="ikskontrollen" metaValue=""/>
            <signavio:signavioMetaData metaKey="istgesamtverantwortlich" metaValue=""/>
            <signavio:signavioMetaData metaKey="urlInfo2" metaValue=""/>
            <signavio:signavioMetaData metaKey="meta-ubmclicks" metaValue=""/>
            <signavio:signavioMetaData metaKey="urlInfo1" metaValue=""/>
            <signavio:signavioMetaData metaKey="additionalresponsible" metaValue=""/>
            <signavio:signavioMetaData metaKey="meta-arissapid" metaValue=""/>
            <signavio:signavioMetaData metaKey="consulted" metaValue=""/>
            <signavio:signavioMetaData metaKey="booleanInfo" metaValue=""/>
            <signavio:signavioMetaData metaKey="meta-sh" metaValue=""/>
            <signavio:signavioMetaData metaKey="meta-automatisiert" metaValue=""/>
            <signavio:signavioMetaData metaKey="meta-riskcontrol" metaValue=""/>
            <signavio:signavioMetaData metaKey="risks" metaValue=""/>
            <signavio:signavioMetaData metaKey="meta-dokumentenobjekte" metaValue=""/>
            <signavio:signavioMetaData metaKey="processlink" metaValue=""/>
            <signavio:signavioMetaData metaKey="meta-risikenundkontrollen" metaValue=""/>
            <signavio:signavioMetaData metaKey="meta-risks" metaValue=""/>
            <signavio:signavioMetaData metaKey="meta-capability" metaValue=""/>
            <signavio:signavioMetaData metaKey="meta-itsysteme" metaValue=""/>
            <signavio:signavioMetaData metaKey="bearbeitungszeiten" metaValue=""/>
            <signavio:signavioMetaData metaKey="risk" metaValue=""/>
            <signavio:signavioMetaData metaKey="meta-mtmexperiencejourney" metaValue=""/>
            <signavio:signavioMetaData metaKey="meta-momentthatmatters2" metaValue=""/>
         </extensionElements>
         <incoming>sid-556F8EB4-4CB9-4370-9D83-4BCABC759443</incoming>
         <outgoing>sid-4E7404D6-ABC8-4A2D-9C3D-3ED593867730</outgoing>
      </task>
      <task completionQuantity="1" id="sid-D76A99F6-2768-4ED0-841C-171162FB9077" isForCompensation="false" name="2" startQuantity="1">
         <extensionElements>
            <signavio:signavioMetaData metaKey="bgcolor" metaValue="#FFFFFF"/>
            <signavio:signavioMetaData metaKey="bordercolor" metaValue="#000000"/>
            <signavio:signavioMetaData metaKey="meta-solutionprocessflows" metaValue=""/>
            <signavio:signavioMetaData metaKey="meta-responsible" metaValue=""/>
            <signavio:signavioMetaData metaKey="erteiltfreigabe" metaValue=""/>
            <signavio:signavioMetaData metaKey="clbcpid" metaValue="N/A"/>
            <signavio:signavioMetaData metaKey="wirdkonsultiert" metaValue=""/>
            <signavio:signavioMetaData metaKey="meta-clriskid" metaValue="N/A"/>
            <signavio:signavioMetaData metaKey="meta-executioncosts" metaValue=""/>
            <signavio:signavioMetaData metaKey="meta-date" metaValue=""/>
            <signavio:signavioMetaData metaKey="meta-accountable" metaValue=""/>
            <signavio:signavioMetaData metaKey="iks" metaValue=""/>
            <signavio:signavioMetaData metaKey="fhrtzustzlichdurch" metaValue=""/>
            <signavio:signavioMetaData metaKey="itsystems" metaValue=""/>
            <signavio:signavioMetaData metaKey="meta-erteiltfreigabe2" metaValue=""/>
            <signavio:signavioMetaData metaKey="clrqid" metaValue="N/A"/>
            <signavio:signavioMetaData metaKey="meta-myglossarylink" metaValue=""/>
            <signavio:signavioMetaData metaKey="meta-screenflow" metaValue=""/>
            <signavio:signavioMetaData metaKey="meta-informed" metaValue=""/>
            <signavio:signavioMetaData metaKey="mitgeltendedokumente" metaValue=""/>
            <signavio:signavioMetaData metaKey="startid" metaValue=""/>
            <signavio:signavioMetaData metaKey="meta-ml" metaValue=""/>
            <signavio:signavioMetaData metaKey="additionallyresponsible" metaValue=""/>
            <signavio:signavioMetaData metaKey="booleanInfo2" metaValue=""/>
            <signavio:signavioMetaData metaKey="meta-processinsightsmetricsavail" metaValue=""/>
            <signavio:signavioMetaData metaKey="myDateIshInfo" metaValue=""/>
            <signavio:signavioMetaData metaKey="isresponsible" metaValue=""/>
            <signavio:signavioMetaData metaKey="accountable" metaValue=""/>
            <signavio:signavioMetaData metaKey="endanchor" metaValue=""/>
            <signavio:signavioMetaData metaKey="slbespokeflag" metaValue="No"/>
            <signavio:signavioMetaData metaKey="meta-istgesamtverwantwortlich" metaValue=""/>
            <signavio:signavioMetaData metaKey="externaldocuments2" metaValue=""/>
            <signavio:signavioMetaData metaKey="ikskontrolle" metaValue=""/>
            <signavio:signavioMetaData metaKey="sla" metaValue=""/>
            <signavio:signavioMetaData metaKey="meta-arissaptype" metaValue=""/>
            <signavio:signavioMetaData metaKey="meta-processinsightsmetricdetail" metaValue=""/>
            <signavio:signavioMetaData metaKey="externaldocuments" metaValue=""/>
            <signavio:signavioMetaData metaKey="meta-bestpracticedocument" metaValue=""/>
            <signavio:signavioMetaData metaKey="vorlagenliste" metaValue=""/>
            <signavio:signavioMetaData metaKey="meta-externaldocuments" metaValue=""/>
            <signavio:signavioMetaData metaKey="prozessrelevantedokumente" metaValue=""/>
            <signavio:signavioMetaData metaKey="meta-erteiltfreigabe" metaValue=""/>
            <signavio:signavioMetaData metaKey="meta-riskandcontrols" metaValue=""/>
            <signavio:signavioMetaData metaKey="meta-importance" metaValue=""/>
            <signavio:signavioMetaData metaKey="risksactivity" metaValue=""/>
            <signavio:signavioMetaData metaKey="systemid" metaValue=""/>
            <signavio:signavioMetaData metaKey="meta-itsystem" metaValue=""/>
            <signavio:signavioMetaData metaKey="meta-mcdtaskactivityprerequisite" metaValue=""/>
            <signavio:signavioMetaData metaKey="meta-erteiltfreigabe22" metaValue=""/>
            <signavio:signavioMetaData metaKey="doclink" metaValue=""/>
            <signavio:signavioMetaData metaKey="fhrtdurch" metaValue=""/>
            <signavio:signavioMetaData metaKey="myDateIshInfo2" metaValue=""/>
            <signavio:signavioMetaData metaKey="zahl" metaValue=""/>
            <signavio:signavioMetaData metaKey="meta-consulted" metaValue=""/>
            <signavio:signavioMetaData metaKey="innererevision" metaValue=""/>
            <signavio:signavioMetaData metaKey="cliscontrolflag" metaValue=""/>
            <signavio:signavioMetaData metaKey="responsible" metaValue=""/>
            <signavio:signavioMetaData metaKey="meta-externaldocuments2" metaValue=""/>
            <signavio:signavioMetaData metaKey="liegezeiten" metaValue=""/>
            <signavio:signavioMetaData metaKey="meta-signalmetricsavailabletomea" metaValue=""/>
            <signavio:signavioMetaData metaKey="meta-issues" metaValue=""/>
            <signavio:signavioMetaData metaKey="wirdinformiert" metaValue=""/>
            <signavio:signavioMetaData metaKey="informed" metaValue=""/>
            <signavio:signavioMetaData metaKey="risikenundkontrollen" metaValue=""/>
            <signavio:signavioMetaData metaKey="meta-risklevel" metaValue="None"/>
            <signavio:signavioMetaData metaKey="ikskontrollen" metaValue=""/>
            <signavio:signavioMetaData metaKey="istgesamtverantwortlich" metaValue=""/>
            <signavio:signavioMetaData metaKey="urlInfo2" metaValue=""/>
            <signavio:signavioMetaData metaKey="meta-ubmclicks" metaValue=""/>
            <signavio:signavioMetaData metaKey="urlInfo1" metaValue=""/>
            <signavio:signavioMetaData metaKey="additionalresponsible" metaValue=""/>
            <signavio:signavioMetaData metaKey="meta-arissapid" metaValue=""/>
            <signavio:signavioMetaData metaKey="consulted" metaValue=""/>
            <signavio:signavioMetaData metaKey="booleanInfo" metaValue=""/>
            <signavio:signavioMetaData metaKey="meta-sh" metaValue=""/>
            <signavio:signavioMetaData metaKey="meta-automatisiert" metaValue=""/>
            <signavio:signavioMetaData metaKey="meta-riskcontrol" metaValue=""/>
            <signavio:signavioMetaData metaKey="risks" metaValue=""/>
            <signavio:signavioMetaData metaKey="meta-dokumentenobjekte" metaValue=""/>
            <signavio:signavioMetaData metaKey="processlink" metaValue=""/>
            <signavio:signavioMetaData metaKey="meta-risikenundkontrollen" metaValue=""/>
            <signavio:signavioMetaData metaKey="meta-risks" metaValue=""/>
            <signavio:signavioMetaData metaKey="meta-capability" metaValue=""/>
            <signavio:signavioMetaData metaKey="meta-itsysteme" metaValue=""/>
            <signavio:signavioMetaData metaKey="bearbeitungszeiten" metaValue=""/>
            <signavio:signavioMetaData metaKey="risk" metaValue=""/>
            <signavio:signavioMetaData metaKey="meta-mtmexperiencejourney" metaValue=""/>
            <signavio:signavioMetaData metaKey="meta-momentthatmatters2" metaValue=""/>
         </extensionElements>
         <incoming>sid-5867DA7E-63B0-47C4-845D-ED539FE1A66C</incoming>
         <outgoing>sid-1E64C13B-6E9F-48FE-AF83-F1BE22730B74</outgoing>
      </task>
      <task completionQuantity="1" id="sid-29940651-400D-43AD-BA8D-7EC276331D33" isForCompensation="false" name="3" startQuantity="1">
         <extensionElements>
            <signavio:signavioMetaData metaKey="bgcolor" metaValue="#FFFFFF"/>
            <signavio:signavioMetaData metaKey="bordercolor" metaValue="#000000"/>
            <signavio:signavioMetaData metaKey="meta-solutionprocessflows" metaValue=""/>
            <signavio:signavioMetaData metaKey="meta-responsible" metaValue=""/>
            <signavio:signavioMetaData metaKey="erteiltfreigabe" metaValue=""/>
            <signavio:signavioMetaData metaKey="clbcpid" metaValue="N/A"/>
            <signavio:signavioMetaData metaKey="wirdkonsultiert" metaValue=""/>
            <signavio:signavioMetaData metaKey="meta-clriskid" metaValue="N/A"/>
            <signavio:signavioMetaData metaKey="meta-executioncosts" metaValue=""/>
            <signavio:signavioMetaData metaKey="meta-date" metaValue=""/>
            <signavio:signavioMetaData metaKey="meta-accountable" metaValue=""/>
            <signavio:signavioMetaData metaKey="iks" metaValue=""/>
            <signavio:signavioMetaData metaKey="fhrtzustzlichdurch" metaValue=""/>
            <signavio:signavioMetaData metaKey="itsystems" metaValue=""/>
            <signavio:signavioMetaData metaKey="meta-erteiltfreigabe2" metaValue=""/>
            <signavio:signavioMetaData metaKey="clrqid" metaValue="N/A"/>
            <signavio:signavioMetaData metaKey="meta-myglossarylink" metaValue=""/>
            <signavio:signavioMetaData metaKey="meta-screenflow" metaValue=""/>
            <signavio:signavioMetaData metaKey="meta-informed" metaValue=""/>
            <signavio:signavioMetaData metaKey="mitgeltendedokumente" metaValue=""/>
            <signavio:signavioMetaData metaKey="startid" metaValue=""/>
            <signavio:signavioMetaData metaKey="meta-ml" metaValue=""/>
            <signavio:signavioMetaData metaKey="additionallyresponsible" metaValue=""/>
            <signavio:signavioMetaData metaKey="booleanInfo2" metaValue=""/>
            <signavio:signavioMetaData metaKey="meta-processinsightsmetricsavail" metaValue=""/>
            <signavio:signavioMetaData metaKey="myDateIshInfo" metaValue=""/>
            <signavio:signavioMetaData metaKey="isresponsible" metaValue=""/>
            <signavio:signavioMetaData metaKey="accountable" metaValue=""/>
            <signavio:signavioMetaData metaKey="endanchor" metaValue=""/>
            <signavio:signavioMetaData metaKey="slbespokeflag" metaValue="No"/>
            <signavio:signavioMetaData metaKey="meta-istgesamtverwantwortlich" metaValue=""/>
            <signavio:signavioMetaData metaKey="externaldocuments2" metaValue=""/>
            <signavio:signavioMetaData metaKey="ikskontrolle" metaValue=""/>
            <signavio:signavioMetaData metaKey="sla" metaValue=""/>
            <signavio:signavioMetaData metaKey="meta-arissaptype" metaValue=""/>
            <signavio:signavioMetaData metaKey="meta-processinsightsmetricdetail" metaValue=""/>
            <signavio:signavioMetaData metaKey="externaldocuments" metaValue=""/>
            <signavio:signavioMetaData metaKey="meta-bestpracticedocument" metaValue=""/>
            <signavio:signavioMetaData metaKey="vorlagenliste" metaValue=""/>
            <signavio:signavioMetaData metaKey="meta-externaldocuments" metaValue=""/>
            <signavio:signavioMetaData metaKey="prozessrelevantedokumente" metaValue=""/>
            <signavio:signavioMetaData metaKey="meta-erteiltfreigabe" metaValue=""/>
            <signavio:signavioMetaData metaKey="meta-riskandcontrols" metaValue=""/>
            <signavio:signavioMetaData metaKey="meta-importance" metaValue=""/>
            <signavio:signavioMetaData metaKey="risksactivity" metaValue=""/>
            <signavio:signavioMetaData metaKey="systemid" metaValue=""/>
            <signavio:signavioMetaData metaKey="meta-itsystem" metaValue=""/>
            <signavio:signavioMetaData metaKey="meta-mcdtaskactivityprerequisite" metaValue=""/>
            <signavio:signavioMetaData metaKey="meta-erteiltfreigabe22" metaValue=""/>
            <signavio:signavioMetaData metaKey="doclink" metaValue=""/>
            <signavio:signavioMetaData metaKey="fhrtdurch" metaValue=""/>
            <signavio:signavioMetaData metaKey="myDateIshInfo2" metaValue=""/>
            <signavio:signavioMetaData metaKey="zahl" metaValue=""/>
            <signavio:signavioMetaData metaKey="meta-consulted" metaValue=""/>
            <signavio:signavioMetaData metaKey="innererevision" metaValue=""/>
            <signavio:signavioMetaData metaKey="cliscontrolflag" metaValue=""/>
            <signavio:signavioMetaData metaKey="responsible" metaValue=""/>
            <signavio:signavioMetaData metaKey="meta-externaldocuments2" metaValue=""/>
            <signavio:signavioMetaData metaKey="liegezeiten" metaValue=""/>
            <signavio:signavioMetaData metaKey="meta-signalmetricsavailabletomea" metaValue=""/>
            <signavio:signavioMetaData metaKey="meta-issues" metaValue=""/>
            <signavio:signavioMetaData metaKey="wirdinformiert" metaValue=""/>
            <signavio:signavioMetaData metaKey="informed" metaValue=""/>
            <signavio:signavioMetaData metaKey="risikenundkontrollen" metaValue=""/>
            <signavio:signavioMetaData metaKey="meta-risklevel" metaValue="None"/>
            <signavio:signavioMetaData metaKey="ikskontrollen" metaValue=""/>
            <signavio:signavioMetaData metaKey="istgesamtverantwortlich" metaValue=""/>
            <signavio:signavioMetaData metaKey="urlInfo2" metaValue=""/>
            <signavio:signavioMetaData metaKey="meta-ubmclicks" metaValue=""/>
            <signavio:signavioMetaData metaKey="urlInfo1" metaValue=""/>
            <signavio:signavioMetaData metaKey="additionalresponsible" metaValue=""/>
            <signavio:signavioMetaData metaKey="meta-arissapid" metaValue=""/>
            <signavio:signavioMetaData metaKey="consulted" metaValue=""/>
            <signavio:signavioMetaData metaKey="booleanInfo" metaValue=""/>
            <signavio:signavioMetaData metaKey="meta-sh" metaValue=""/>
            <signavio:signavioMetaData metaKey="meta-automatisiert" metaValue=""/>
            <signavio:signavioMetaData metaKey="meta-riskcontrol" metaValue=""/>
            <signavio:signavioMetaData metaKey="risks" metaValue=""/>
            <signavio:signavioMetaData metaKey="meta-dokumentenobjekte" metaValue=""/>
            <signavio:signavioMetaData metaKey="processlink" metaValue=""/>
            <signavio:signavioMetaData metaKey="meta-risikenundkontrollen" metaValue=""/>
            <signavio:signavioMetaData metaKey="meta-risks" metaValue=""/>
            <signavio:signavioMetaData metaKey="meta-capability" metaValue=""/>
            <signavio:signavioMetaData metaKey="meta-itsysteme" metaValue=""/>
            <signavio:signavioMetaData metaKey="bearbeitungszeiten" metaValue=""/>
            <signavio:signavioMetaData metaKey="risk" metaValue=""/>
            <signavio:signavioMetaData metaKey="meta-mtmexperiencejourney" metaValue=""/>
            <signavio:signavioMetaData metaKey="meta-momentthatmatters2" metaValue=""/>
         </extensionElements>
         <incoming>sid-DA60A646-4E09-46FC-B8B5-414DE5D41C8F</incoming>
         <outgoing>sid-3FF3AA08-B82F-4386-99FF-116B9B157DBA</outgoing>
      </task>
      <inclusiveGateway gatewayDirection="Converging" id="sid-6687DB4D-A36A-4BD0-8C24-D34F4DE05727">
         <extensionElements>
            <signavio:signavioMetaData metaKey="bgcolor" metaValue="#ffffff"/>
            <signavio:signavioMetaData metaKey="bordercolor" metaValue="#000000"/>
            <signavio:signavioMetaData metaKey="adapterclassname" metaValue=""/>
            <signavio:signavioMetaData metaKey="adaptertype" metaValue=""/>
            <signavio:signavioMetaData metaKey="psiconfiguration" metaValue=""/>
         </extensionElements>
         <incoming>sid-4E7404D6-ABC8-4A2D-9C3D-3ED593867730</incoming>
         <incoming>sid-1E64C13B-6E9F-48FE-AF83-F1BE22730B74</incoming>
         <incoming>sid-3FF3AA08-B82F-4386-99FF-116B9B157DBA</incoming>
         <outgoing>sid-A9C805CD-F54B-4827-8B9B-11CDC45CB2C3</outgoing>
      </inclusiveGateway>
      <task completionQuantity="1" id="sid-8E60DB04-AFC4-4DF3-A18B-D81050A3A43E" isForCompensation="false" name="4" startQuantity="1">
         <extensionElements>
            <signavio:signavioMetaData metaKey="bgcolor" metaValue="#FFFFFF"/>
            <signavio:signavioMetaData metaKey="bordercolor" metaValue="#000000"/>
            <signavio:signavioMetaData metaKey="meta-solutionprocessflows" metaValue=""/>
            <signavio:signavioMetaData metaKey="meta-responsible" metaValue=""/>
            <signavio:signavioMetaData metaKey="erteiltfreigabe" metaValue=""/>
            <signavio:signavioMetaData metaKey="clbcpid" metaValue="N/A"/>
            <signavio:signavioMetaData metaKey="wirdkonsultiert" metaValue=""/>
            <signavio:signavioMetaData metaKey="meta-clriskid" metaValue="N/A"/>
            <signavio:signavioMetaData metaKey="meta-executioncosts" metaValue=""/>
            <signavio:signavioMetaData metaKey="meta-date" metaValue=""/>
            <signavio:signavioMetaData metaKey="meta-accountable" metaValue=""/>
            <signavio:signavioMetaData metaKey="iks" metaValue=""/>
            <signavio:signavioMetaData metaKey="fhrtzustzlichdurch" metaValue=""/>
            <signavio:signavioMetaData metaKey="itsystems" metaValue=""/>
            <signavio:signavioMetaData metaKey="meta-erteiltfreigabe2" metaValue=""/>
            <signavio:signavioMetaData metaKey="clrqid" metaValue="N/A"/>
            <signavio:signavioMetaData metaKey="meta-myglossarylink" metaValue=""/>
            <signavio:signavioMetaData metaKey="meta-screenflow" metaValue=""/>
            <signavio:signavioMetaData metaKey="meta-informed" metaValue=""/>
            <signavio:signavioMetaData metaKey="mitgeltendedokumente" metaValue=""/>
            <signavio:signavioMetaData metaKey="startid" metaValue=""/>
            <signavio:signavioMetaData metaKey="meta-ml" metaValue=""/>
            <signavio:signavioMetaData metaKey="additionallyresponsible" metaValue=""/>
            <signavio:signavioMetaData metaKey="booleanInfo2" metaValue=""/>
            <signavio:signavioMetaData metaKey="meta-processinsightsmetricsavail" metaValue=""/>
            <signavio:signavioMetaData metaKey="myDateIshInfo" metaValue=""/>
            <signavio:signavioMetaData metaKey="isresponsible" metaValue=""/>
            <signavio:signavioMetaData metaKey="accountable" metaValue=""/>
            <signavio:signavioMetaData metaKey="endanchor" metaValue=""/>
            <signavio:signavioMetaData metaKey="slbespokeflag" metaValue="No"/>
            <signavio:signavioMetaData metaKey="meta-istgesamtverwantwortlich" metaValue=""/>
            <signavio:signavioMetaData metaKey="externaldocuments2" metaValue=""/>
            <signavio:signavioMetaData metaKey="ikskontrolle" metaValue=""/>
            <signavio:signavioMetaData metaKey="sla" metaValue=""/>
            <signavio:signavioMetaData metaKey="meta-arissaptype" metaValue=""/>
            <signavio:signavioMetaData metaKey="meta-processinsightsmetricdetail" metaValue=""/>
            <signavio:signavioMetaData metaKey="externaldocuments" metaValue=""/>
            <signavio:signavioMetaData metaKey="meta-bestpracticedocument" metaValue=""/>
            <signavio:signavioMetaData metaKey="vorlagenliste" metaValue=""/>
            <signavio:signavioMetaData metaKey="meta-externaldocuments" metaValue=""/>
            <signavio:signavioMetaData metaKey="prozessrelevantedokumente" metaValue=""/>
            <signavio:signavioMetaData metaKey="meta-erteiltfreigabe" metaValue=""/>
            <signavio:signavioMetaData metaKey="meta-riskandcontrols" metaValue=""/>
            <signavio:signavioMetaData metaKey="meta-importance" metaValue=""/>
            <signavio:signavioMetaData metaKey="risksactivity" metaValue=""/>
            <signavio:signavioMetaData metaKey="systemid" metaValue=""/>
            <signavio:signavioMetaData metaKey="meta-itsystem" metaValue=""/>
            <signavio:signavioMetaData metaKey="meta-mcdtaskactivityprerequisite" metaValue=""/>
            <signavio:signavioMetaData metaKey="meta-erteiltfreigabe22" metaValue=""/>
            <signavio:signavioMetaData metaKey="doclink" metaValue=""/>
            <signavio:signavioMetaData metaKey="fhrtdurch" metaValue=""/>
            <signavio:signavioMetaData metaKey="myDateIshInfo2" metaValue=""/>
            <signavio:signavioMetaData metaKey="zahl" metaValue=""/>
            <signavio:signavioMetaData metaKey="meta-consulted" metaValue=""/>
            <signavio:signavioMetaData metaKey="innererevision" metaValue=""/>
            <signavio:signavioMetaData metaKey="cliscontrolflag" metaValue=""/>
            <signavio:signavioMetaData metaKey="responsible" metaValue=""/>
            <signavio:signavioMetaData metaKey="meta-externaldocuments2" metaValue=""/>
            <signavio:signavioMetaData metaKey="liegezeiten" metaValue=""/>
            <signavio:signavioMetaData metaKey="meta-signalmetricsavailabletomea" metaValue=""/>
            <signavio:signavioMetaData metaKey="meta-issues" metaValue=""/>
            <signavio:signavioMetaData metaKey="wirdinformiert" metaValue=""/>
            <signavio:signavioMetaData metaKey="informed" metaValue=""/>
            <signavio:signavioMetaData metaKey="risikenundkontrollen" metaValue=""/>
            <signavio:signavioMetaData metaKey="meta-risklevel" metaValue="None"/>
            <signavio:signavioMetaData metaKey="ikskontrollen" metaValue=""/>
            <signavio:signavioMetaData metaKey="istgesamtverantwortlich" metaValue=""/>
            <signavio:signavioMetaData metaKey="urlInfo2" metaValue=""/>
            <signavio:signavioMetaData metaKey="meta-ubmclicks" metaValue=""/>
            <signavio:signavioMetaData metaKey="urlInfo1" metaValue=""/>
            <signavio:signavioMetaData metaKey="additionalresponsible" metaValue=""/>
            <signavio:signavioMetaData metaKey="meta-arissapid" metaValue=""/>
            <signavio:signavioMetaData metaKey="consulted" metaValue=""/>
            <signavio:signavioMetaData metaKey="booleanInfo" metaValue=""/>
            <signavio:signavioMetaData metaKey="meta-sh" metaValue=""/>
            <signavio:signavioMetaData metaKey="meta-automatisiert" metaValue=""/>
            <signavio:signavioMetaData metaKey="meta-riskcontrol" metaValue=""/>
            <signavio:signavioMetaData metaKey="risks" metaValue=""/>
            <signavio:signavioMetaData metaKey="meta-dokumentenobjekte" metaValue=""/>
            <signavio:signavioMetaData metaKey="processlink" metaValue=""/>
            <signavio:signavioMetaData metaKey="meta-risikenundkontrollen" metaValue=""/>
            <signavio:signavioMetaData metaKey="meta-risks" metaValue=""/>
            <signavio:signavioMetaData metaKey="meta-capability" metaValue=""/>
            <signavio:signavioMetaData metaKey="meta-itsysteme" metaValue=""/>
            <signavio:signavioMetaData metaKey="bearbeitungszeiten" metaValue=""/>
            <signavio:signavioMetaData metaKey="risk" metaValue=""/>
            <signavio:signavioMetaData metaKey="meta-mtmexperiencejourney" metaValue=""/>
            <signavio:signavioMetaData metaKey="meta-momentthatmatters2" metaValue=""/>
         </extensionElements>
         <incoming>sid-A9C805CD-F54B-4827-8B9B-11CDC45CB2C3</incoming>
         <outgoing>sid-BF4F50B5-1556-4A3C-9D2A-A0A0C347DEB5</outgoing>
      </task>
      <sequenceFlow id="sid-556F8EB4-4CB9-4370-9D83-4BCABC759443" sourceRef="sid-71173100-A04C-4DD0-AA9E-768DF423C145" targetRef="sid-AD61A674-0B58-41F2-B14D-53A0F6A0ED9A">
         <extensionElements>
            <signavio:signavioMetaData metaKey="bordercolor" metaValue="#000000"/>
            <signavio:signavioMetaData metaKey="transportzeiten" metaValue=""/>
         </extensionElements>
      </sequenceFlow>
      <sequenceFlow id="sid-5867DA7E-63B0-47C4-845D-ED539FE1A66C" sourceRef="sid-71173100-A04C-4DD0-AA9E-768DF423C145" targetRef="sid-D76A99F6-2768-4ED0-841C-171162FB9077">
         <extensionElements>
            <signavio:signavioMetaData metaKey="bordercolor" metaValue="#000000"/>
            <signavio:signavioMetaData metaKey="transportzeiten" metaValue=""/>
         </extensionElements>
      </sequenceFlow>
      <sequenceFlow id="sid-DA60A646-4E09-46FC-B8B5-414DE5D41C8F" sourceRef="sid-71173100-A04C-4DD0-AA9E-768DF423C145" targetRef="sid-29940651-400D-43AD-BA8D-7EC276331D33">
         <extensionElements>
            <signavio:signavioMetaData metaKey="bordercolor" metaValue="#000000"/>
            <signavio:signavioMetaData metaKey="transportzeiten" metaValue=""/>
         </extensionElements>
      </sequenceFlow>
      <sequenceFlow id="sid-4E7404D6-ABC8-4A2D-9C3D-3ED593867730" sourceRef="sid-AD61A674-0B58-41F2-B14D-53A0F6A0ED9A" targetRef="sid-6687DB4D-A36A-4BD0-8C24-D34F4DE05727">
         <extensionElements>
            <signavio:signavioMetaData metaKey="bordercolor" metaValue="#000000"/>
            <signavio:signavioMetaData metaKey="transportzeiten" metaValue=""/>
         </extensionElements>
      </sequenceFlow>
      <sequenceFlow id="sid-1E64C13B-6E9F-48FE-AF83-F1BE22730B74" sourceRef="sid-D76A99F6-2768-4ED0-841C-171162FB9077" targetRef="sid-6687DB4D-A36A-4BD0-8C24-D34F4DE05727">
         <extensionElements>
            <signavio:signavioMetaData metaKey="bordercolor" metaValue="#000000"/>
            <signavio:signavioMetaData metaKey="transportzeiten" metaValue=""/>
         </extensionElements>
      </sequenceFlow>
      <sequenceFlow id="sid-3FF3AA08-B82F-4386-99FF-116B9B157DBA" sourceRef="sid-29940651-400D-43AD-BA8D-7EC276331D33" targetRef="sid-6687DB4D-A36A-4BD0-8C24-D34F4DE05727">
         <extensionElements>
            <signavio:signavioMetaData metaKey="bordercolor" metaValue="#000000"/>
            <signavio:signavioMetaData metaKey="transportzeiten" metaValue=""/>
         </extensionElements>
      </sequenceFlow>
      <sequenceFlow id="sid-651B3646-CE12-4318-AD49-0E4A923044EC" sourceRef="sid-5F5D86D5-D873-489A-8300-D35D4386FAD5" targetRef="sid-EDFCFD39-8583-45B8-91B3-8E1A9CE45900">
         <extensionElements>
            <signavio:signavioMetaData metaKey="bordercolor" metaValue="#000000"/>
            <signavio:signavioMetaData metaKey="transportzeiten" metaValue=""/>
         </extensionElements>
      </sequenceFlow>
      <sequenceFlow id="sid-7D9767FF-E6EB-4152-9C65-1B11D6262E68" sourceRef="sid-EDFCFD39-8583-45B8-91B3-8E1A9CE45900" targetRef="sid-71173100-A04C-4DD0-AA9E-768DF423C145">
         <extensionElements>
            <signavio:signavioMetaData metaKey="bordercolor" metaValue="#000000"/>
            <signavio:signavioMetaData metaKey="transportzeiten" metaValue=""/>
         </extensionElements>
      </sequenceFlow>
      <sequenceFlow id="sid-A9C805CD-F54B-4827-8B9B-11CDC45CB2C3" sourceRef="sid-6687DB4D-A36A-4BD0-8C24-D34F4DE05727" targetRef="sid-8E60DB04-AFC4-4DF3-A18B-D81050A3A43E">
         <extensionElements>
            <signavio:signavioMetaData metaKey="bordercolor" metaValue="#000000"/>
            <signavio:signavioMetaData metaKey="transportzeiten" metaValue=""/>
         </extensionElements>
      </sequenceFlow>
      <sequenceFlow id="sid-BF4F50B5-1556-4A3C-9D2A-A0A0C347DEB5" sourceRef="sid-8E60DB04-AFC4-4DF3-A18B-D81050A3A43E" targetRef="sid-FC1426C9-AAE7-473D-BAE8-6F10C59B7A74">
         <extensionElements>
            <signavio:signavioMetaData metaKey="bordercolor" metaValue="#000000"/>
            <signavio:signavioMetaData metaKey="transportzeiten" metaValue=""/>
         </extensionElements>
      </sequenceFlow>
   </process>
   <bpmndi:BPMNDiagram id="sid-f8dc3802-8208-41ab-891e-b7ccb8ce459c">
      <bpmndi:BPMNPlane bpmnElement="sid-76bcbdd2-77ac-46fe-9697-d3b32af00f83" id="sid-de08d647-c907-49d3-9b34-7974e4fa538f">
         <bpmndi:BPMNShape bpmnElement="sid-5F5D86D5-D873-489A-8300-D35D4386FAD5" id="sid-5F5D86D5-D873-489A-8300-D35D4386FAD5_gui">
            <omgdc:Bounds height="30.0" width="30.0" x="90.0" y="270.0"/>
         </bpmndi:BPMNShape>
         <bpmndi:BPMNShape bpmnElement="sid-FC1426C9-AAE7-473D-BAE8-6F10C59B7A74" id="sid-FC1426C9-AAE7-473D-BAE8-6F10C59B7A74_gui">
            <omgdc:Bounds height="28.0" width="28.0" x="790.0" y="271.0"/>
         </bpmndi:BPMNShape>
         <bpmndi:BPMNShape bpmnElement="sid-EDFCFD39-8583-45B8-91B3-8E1A9CE45900" id="sid-EDFCFD39-8583-45B8-91B3-8E1A9CE45900_gui">
            <omgdc:Bounds height="80.0" width="100.0" x="165.0" y="245.0"/>
            <bpmndi:BPMNLabel labelStyle="sid-2f7e3c12-29c6-4c7a-a276-ae5026b31a75">
               <omgdc:Bounds height="12.0" width="6.9428558349609375" x="211.52857208251953" y="277.0"/>
            </bpmndi:BPMNLabel>
         </bpmndi:BPMNShape>
         <bpmndi:BPMNShape bpmnElement="sid-71173100-A04C-4DD0-AA9E-768DF423C145" id="sid-71173100-A04C-4DD0-AA9E-768DF423C145_gui">
            <omgdc:Bounds height="40.0" width="40.0" x="310.0" y="265.0"/>
         </bpmndi:BPMNShape>
         <bpmndi:BPMNShape bpmnElement="sid-AD61A674-0B58-41F2-B14D-53A0F6A0ED9A" id="sid-AD61A674-0B58-41F2-B14D-53A0F6A0ED9A_gui">
            <omgdc:Bounds height="80.0" width="100.0" x="395.0" y="120.0"/>
            <bpmndi:BPMNLabel labelStyle="sid-2f7e3c12-29c6-4c7a-a276-ae5026b31a75">
               <omgdc:Bounds height="12.0" width="6.9428558349609375" x="441.52857208251953" y="152.0"/>
            </bpmndi:BPMNLabel>
         </bpmndi:BPMNShape>
         <bpmndi:BPMNShape bpmnElement="sid-D76A99F6-2768-4ED0-841C-171162FB9077" id="sid-D76A99F6-2768-4ED0-841C-171162FB9077_gui">
            <omgdc:Bounds height="80.0" width="100.0" x="395.0" y="245.0"/>
            <bpmndi:BPMNLabel labelStyle="sid-2f7e3c12-29c6-4c7a-a276-ae5026b31a75">
               <omgdc:Bounds height="12.0" width="6.9428558349609375" x="441.52857208251953" y="277.0"/>
            </bpmndi:BPMNLabel>
         </bpmndi:BPMNShape>
         <bpmndi:BPMNShape bpmnElement="sid-29940651-400D-43AD-BA8D-7EC276331D33" id="sid-29940651-400D-43AD-BA8D-7EC276331D33_gui">
            <omgdc:Bounds height="80.0" width="100.0" x="395.0" y="370.0"/>
            <bpmndi:BPMNLabel labelStyle="sid-2f7e3c12-29c6-4c7a-a276-ae5026b31a75">
               <omgdc:Bounds height="12.0" width="6.9428558349609375" x="441.52857208251953" y="402.0"/>
            </bpmndi:BPMNLabel>
         </bpmndi:BPMNShape>
         <bpmndi:BPMNShape bpmnElement="sid-6687DB4D-A36A-4BD0-8C24-D34F4DE05727" id="sid-6687DB4D-A36A-4BD0-8C24-D34F4DE05727_gui">
            <omgdc:Bounds height="40.0" width="40.0" x="550.0" y="265.0"/>
         </bpmndi:BPMNShape>
         <bpmndi:BPMNShape bpmnElement="sid-8E60DB04-AFC4-4DF3-A18B-D81050A3A43E" id="sid-8E60DB04-AFC4-4DF3-A18B-D81050A3A43E_gui">
            <omgdc:Bounds height="80.0" width="100.0" x="635.0" y="245.0"/>
            <bpmndi:BPMNLabel labelStyle="sid-2f7e3c12-29c6-4c7a-a276-ae5026b31a75">
               <omgdc:Bounds height="12.0" width="6.9428558349609375" x="681.5285720825195" y="277.0"/>
            </bpmndi:BPMNLabel>
         </bpmndi:BPMNShape>
         <bpmndi:BPMNEdge bpmnElement="sid-556F8EB4-4CB9-4370-9D83-4BCABC759443" id="sid-556F8EB4-4CB9-4370-9D83-4BCABC759443_gui">
            <omgdi:waypoint x="330.5" y="265.0"/>
            <omgdi:waypoint x="330.5" y="160.0"/>
            <omgdi:waypoint x="395.0" y="160.0"/>
         </bpmndi:BPMNEdge>
         <bpmndi:BPMNEdge bpmnElement="sid-5867DA7E-63B0-47C4-845D-ED539FE1A66C" id="sid-5867DA7E-63B0-47C4-845D-ED539FE1A66C_gui">
            <omgdi:waypoint x="350.0" y="285.414847161572"/>
            <omgdi:waypoint x="395.0" y="285.2183406113537"/>
         </bpmndi:BPMNEdge>
         <bpmndi:BPMNEdge bpmnElement="sid-DA60A646-4E09-46FC-B8B5-414DE5D41C8F" id="sid-DA60A646-4E09-46FC-B8B5-414DE5D41C8F_gui">
            <omgdi:waypoint x="330.5" y="305.0"/>
            <omgdi:waypoint x="330.5" y="410.0"/>
            <omgdi:waypoint x="395.0" y="410.0"/>
         </bpmndi:BPMNEdge>
         <bpmndi:BPMNEdge bpmnElement="sid-4E7404D6-ABC8-4A2D-9C3D-3ED593867730" id="sid-4E7404D6-ABC8-4A2D-9C3D-3ED593867730_gui">
            <omgdi:waypoint x="495.0" y="160.0"/>
            <omgdi:waypoint x="570.5" y="160.0"/>
            <omgdi:waypoint x="570.5" y="265.0"/>
         </bpmndi:BPMNEdge>
         <bpmndi:BPMNEdge bpmnElement="sid-1E64C13B-6E9F-48FE-AF83-F1BE22730B74" id="sid-1E64C13B-6E9F-48FE-AF83-F1BE22730B74_gui">
            <omgdi:waypoint x="495.0" y="285.199203187251"/>
            <omgdi:waypoint x="550.0" y="285.4183266932271"/>
         </bpmndi:BPMNEdge>
         <bpmndi:BPMNEdge bpmnElement="sid-3FF3AA08-B82F-4386-99FF-116B9B157DBA" id="sid-3FF3AA08-B82F-4386-99FF-116B9B157DBA_gui">
            <omgdi:waypoint x="495.0" y="410.0"/>
            <omgdi:waypoint x="570.5" y="410.0"/>
            <omgdi:waypoint x="570.5" y="305.0"/>
         </bpmndi:BPMNEdge>
         <bpmndi:BPMNEdge bpmnElement="sid-651B3646-CE12-4318-AD49-0E4A923044EC" id="sid-651B3646-CE12-4318-AD49-0E4A923044EC_gui">
            <omgdi:waypoint x="120.0" y="285.0"/>
            <omgdi:waypoint x="165.0" y="285.0"/>
         </bpmndi:BPMNEdge>
         <bpmndi:BPMNEdge bpmnElement="sid-7D9767FF-E6EB-4152-9C65-1B11D6262E68" id="sid-7D9767FF-E6EB-4152-9C65-1B11D6262E68_gui">
            <omgdi:waypoint x="265.0" y="285.2164502164502"/>
            <omgdi:waypoint x="310.0" y="285.4112554112554"/>
         </bpmndi:BPMNEdge>
         <bpmndi:BPMNEdge bpmnElement="sid-A9C805CD-F54B-4827-8B9B-11CDC45CB2C3" id="sid-A9C805CD-F54B-4827-8B9B-11CDC45CB2C3_gui">
            <omgdi:waypoint x="590.0" y="285.414847161572"/>
            <omgdi:waypoint x="635.0" y="285.2183406113537"/>
         </bpmndi:BPMNEdge>
         <bpmndi:BPMNEdge bpmnElement="sid-BF4F50B5-1556-4A3C-9D2A-A0A0C347DEB5" id="sid-BF4F50B5-1556-4A3C-9D2A-A0A0C347DEB5_gui">
            <omgdi:waypoint x="735.0" y="285.0"/>
            <omgdi:waypoint x="790.0" y="285.0"/>
         </bpmndi:BPMNEdge>
      </bpmndi:BPMNPlane>
      <bpmndi:BPMNLabelStyle id="sid-2f7e3c12-29c6-4c7a-a276-ae5026b31a75">
         <omgdc:Font isBold="false" isItalic="false" isStrikeThrough="false" isUnderline="false" name="Arial" size="12.0"/>
      </bpmndi:BPMNLabelStyle>
   </bpmndi:BPMNDiagram>
</definitions>
